{"url": "http://mentalfloss.com/article/62518/emotionally-scar-your-typophile-friends-comic-papyrus", "numServices": "2", "robots": "False", "hostIsLive": "True", "totalscans": "63", "detections": "6", "vt_class": "Benign", "tag": "b_url209", "features": {"entropy": -4.427266198940317, "numDigits": 5, "urlLength": 90, "numParams": 0, "hasHttp": true, "hasHttps": false, "urlIsLive": false, "bodyLength": 12398, "numTitles": 7, "numImages": 4, "numLinks": 122, "scriptLength": 10351, "specialChars": 3280, "ext": "com", "dsr": "8784", "dse": "1808"}}