{"url": "http://torcache.net/torrent/21996EA35668C8FC53F066F290375CA6FCA5683F.torrent?title=[kickass.to]ed.sheeran.plus.2011.album.dvd.by.shun.lim1", "numServices": "1", "robots": "False", "hostIsLive": "True", "totalscans": "76", "detections": "6", "vt_class": "Benign", "tag": "b_url1", "features": {"entropy": -4.9861210943757595, "numDigits": 32, "urlLength": 138, "numParams": 0, "hasHttp": true, "hasHttps": false, "urlIsLive": false, "bodyLength": 3240, "numTitles": 0, "numImages": 0, "numLinks": 0, "scriptLength": 3240, "specialChars": 1123, "ext": "lim1", "dsr": "3286", "dse": "366"}}