{"url": "http://kakaku.com/daily-goods/room-deodorant/ranking_7655/pricedown/div-gpt-ad-k/header_text", "numServices": "2", "robots": "False", "hostIsLive": "True", "totalscans": "76", "detections": "5", "vt_class": "Benign", "tag": "b_url40", "features": {"entropy": -4.468022865178705, "numDigits": 4, "urlLength": 92, "numParams": 0, "hasHttp": true, "hasHttps": false, "urlIsLive": false, "bodyLength": 11544, "numTitles": 10, "numImages": 48, "numLinks": 256, "scriptLength": 5740, "specialChars": 2970, "ext": "com", "dsr": "7964", "dse": "70"}}