{"url": "https://springboardpreschool.com/wp-admin/js/widgets/cs/delta.com/aol/index.php", "numServices": "0", "robots": "False", "hostIsLive": "False", "totalscans": "72", "detections": "18", "vt_class": "Malicious", "tag": "m_url101", "features": {"entropy": -4.2886210581343285, "numDigits": 0, "urlLength": 79, "numParams": 0, "hasHttp": false, "hasHttps": true, "urlIsLive": false, "bodyLength": 14678, "numTitles": 7, "numImages": 2, "numLinks": 29, "scriptLength": 2903, "specialChars": 3771, "ext": "php", "dsr": "2287", "dse": "269"}}